step_by_step/__init__.py
step_by_step/step_by_step.py
task_in_steps/__init__.py
task_in_steps/task_in_steps.py
task_in_steps-0.0.1.dist-info/LICENSE
task_in_steps-0.0.1.dist-info/METADATA
task_in_steps-0.0.1.dist-info/WHEEL
task_in_steps-0.0.1.dist-info/top_level.txt
task_in_steps-0.0.1.dist-info/RECORD
