Metadata-Version: 2.1
Name: task-in-steps
Version: 0.0.1
Summary: Many python-automation scripts can be seperated into steps. This library supports this seperation.
Home-page: https://github.com/tom-010/task_in_steps
Author: Thomas Deniffel
Author-email: tdeniffel@gmail.com
License: Apache2
Platform: UNKNOWN
Classifier: Development Status :: 4 - Beta
Classifier: Intended Audience :: Developers
Classifier: Programming Language :: Python
Classifier: Programming Language :: Python :: 3 :: Only
Classifier: Programming Language :: Python :: 3.6
Classifier: Programming Language :: Python :: 3.7
Requires-Python: >=3
